itest2/__init__.py
itest2/client.py
itest2/database_client.py
itest2/exceptions.py
itest2/http_client.py
itest2/itest_session.py
itest2/json_schema.py
itest2/resources.py
itest2/response_assert.py
itest2/wait.py
itest2-0.1.0.dist-info/WHEEL
itest2-0.1.0.dist-info/METADATA
itest2-0.1.0.dist-info/RECORD
