Metadata-Version: 2.1
Name: itest2
Version: 0.1.0
Summary: 
Author: ZhangHao
Author-email: zhanghao@growingio.com
Requires-Python: >=3.7,<4.0
Classifier: Programming Language :: Python :: 3
Classifier: Programming Language :: Python :: 3.7
Classifier: Programming Language :: Python :: 3.8
Requires-Dist: PyHamcrest (>=2.0.2,<3.0.0)
Requires-Dist: curlify (>=2.2.1,<3.0.0)
Requires-Dist: genson (>=1.2.2,<2.0.0)
Requires-Dist: jsonschema (>=3.2.0,<4.0.0)
Requires-Dist: records (>=0.5.3,<0.6.0)
Requires-Dist: requests (>=2.24.0,<3.0.0)
